{
  "scene": "cable_pile_xl",
  "method": "method_r_warp_10_bend_cable_pile_xl_stiff",
  "config": {
    "iterations": 10,
    "substep_mult": 1,
    "avbd_beta": 0.0,
    "hard": true,
    "fps": 60,
    "sim_substeps": 10,
    "num_frames_requested": 120,
    "num_frames_completed": 120
  },
  "num_frames": 120,
  "fps": 60,
  "substeps": 10,
  "seconds_total": 1379.0356849431992,
  "seconds_step_mean_ms": 69.35269626167913,
  "seconds_step_p50_ms": 69.39007341861725,
  "seconds_step_p95_ms": 69.42537194117904,
  "final_stretch_max": 0.006996154410844858,
  "final_stretch_rms": 0.0001649234528074188,
  "final_bend_max": 0.081706640750354,
  "final_bend_rms": 0.009984240100474022,
  "energy_drift_rel": -0.9079707210443043,
  "max_speed_observed": 5.037730605255299,
  "min_z_observed": 0.0,
  "visual_path": "/home/horde/JC/newton/bench/_workspace/cable_pile_xl/method_r_warp_10_bend_cable_pile_xl_stiff.mp4",
  "timeseries_csv": "/home/horde/JC/newton/bench/_workspace/cable_pile_xl/method_r_warp_10_bend_cable_pile_xl_stiff.csv",
  "notes": "12 layers \u00d7 12 lanes \u00d7 200 segments = 28 800 bodies; bend_ke=5.0 (1.0\u00d7); production scaling stress test.",
  "error": null
}